mcp_bugbot_gitlab/__init__.py
mcp_bugbot_gitlab/context.py
mcp_bugbot_gitlab/gitlab_client.py
mcp_bugbot_gitlab/jira_client.py
mcp_bugbot_gitlab/prompts.py
mcp_bugbot_gitlab/resources.py
mcp_bugbot_gitlab/server.py
mcp_bugbot_gitlab-0.1.1.dist-info/METADATA
mcp_bugbot_gitlab-0.1.1.dist-info/WHEEL
mcp_bugbot_gitlab-0.1.1.dist-info/entry_points.txt
mcp_bugbot_gitlab-0.1.1.dist-info/top_level.txt
mcp_bugbot_gitlab-0.1.1.dist-info/RECORD
