Metadata-Version: 2.4
Name: mcp-bugbot-gitlab
Version: 0.1.1
Summary: MCP server for GitLab merge request management
Home-page: https://github.com/kitlabcode/mcp-bugbot-gitlab
Author: Jonathan Kittell
Classifier: Programming Language :: Python :: 3
Classifier: License :: OSI Approved :: MIT License
Classifier: Operating System :: OS Independent
Requires-Python: >=3.6
Requires-Dist: fastmcp
Requires-Dist: pydantic
Requires-Dist: python-gitlab
Requires-Dist: python-dotenv
Dynamic: author
Dynamic: classifier
Dynamic: description
Dynamic: description-content-type
Dynamic: home-page
Dynamic: requires-dist
Dynamic: requires-python
Dynamic: summary
